{
  "type": "FeatureCollection",
  "features": [
    {
      "type": "Feature",
      "properties": {
        "name": "KoChang",
        "p": 1000
      },
      "geometry": {
        "type": "Polygon",
        "coordinates": [
          [
            [
              1182.4406433105469,
              11.94327285605027
            ],
            [
              1182.4351501464844,
              11.962585890210182
            ],
            [
              1182.4429607391357,
              11.973249452956193
            ],
            [
              1182.4469089508057,
              11.975264567149138
            ],
            [
              1182.444076538086,
              11.98047020923188
            ],
            [
              1182.438325881958,
              11.98399655491484
            ],
            [
              1182.4301719665527,
              11.989705778818758
            ],
            [
              1182.3991870880127,
              12.039908156606792
            ],
            [
              1182.3967838287354,
              12.050065023002462
            ],
            [
              1182.3921489715576,
              12.051491989975055
            ],
            [
              1182.3861408233643,
              12.04763076771671
            ],
            [
              1182.383737564087,
              12.060725122258873
            ],
            [
              1182.3498344421387,
              12.113347899098217
            ],
            [
              1182.3042154312134,
              12.14183708684448
            ],
            [
              1182.2861051559448,
              12.143263564049564
            ],
            [
              1182.2849035263062,
              12.141249711656753
            ],
            [
              1182.2781229019165,
              12.141711220841882
            ],
            [
              1182.2750329971313,
              12.143557249584386
            ],
            [
              1182.278380393982,
              12.146452132522096
            ],
            [
              1182.2777366638184,
              12.147375132057798
            ],
            [
              1182.270483970642,
              12.14418657463969
            ],
            [
              1182.2665786743164,
              12.147584904233193
            ],
            [
              1182.261471748352,
              12.15123491361908
            ],
            [
              1182.2579526901245,
              12.155136592426219
            ],
            [
              1182.2529745101929,
              12.157318151332166
            ],
            [
              1182.2507429122925,
              12.157234245551262
            ],
            [
              1182.2506141662598,
              12.154633153214755
            ],
            [
              1182.2534465789795,
              12.151025144320572
            ],
            [
              1182.2566652297974,
              12.150815374856688
            ],
            [
              1182.2599267959595,
              12.147291223141337
            ],
            [
              1182.2673082351685,
              12.144941762742599
            ],
            [
              1182.268853187561,
              12.14183708684448
            ],
            [
              1182.2653770446777,
              12.132900452868265
            ],
            [
              1182.2588968276978,
              12.133613716352178
            ],
            [
              1182.2494554519653,
              12.137599565382581
            ],
            [
              1182.2529315948484,
              12.129795636641338
            ],
            [
              1182.2593259811401,
              12.123963519222809
            ],
            [
              1182.262930870056,
              12.118718700402773
            ],
            [
              1182.2734451293945,
              12.102312241742732
            ],
            [
              1182.2743463516235,
              12.09819997907324
            ],
            [
              1182.2767496109009,
              12.085275313192353
            ],
            [
              1182.2752475738525,
              12.082841377672
            ],
            [
              1182.2757625579834,
              12.079232398057693
            ],
            [
              1182.276406288147,
              12.075245677979085
            ],
            [
              1182.2748613357542,
              12.07532960953972
            ],
            [
              1182.277307510376,
              12.066516652094192
            ],
            [
              1182.2788524627686,
              12.064166481158317
            ],
            [
              1182.2797107696533,
              12.066642553527087
            ],
            [
              1182.2821140289307,
              12.066558619245056
            ],
            [
              1182.28919506073,
              12.058584742617725
            ],
            [
              1182.2941303253174,
              12.041083350883317
            ],
            [
              1182.290997505188,
              12.032563075918526
            ],
            [
              1182.2877788543701,
              12.015143939577031
            ],
            [
              1182.2938728332517,
              12.002299227818447
            ],
            [
              1182.2975635528564,
              11.997345874721201
            ],
            [
              1182.297649383545,
              11.987270977513951
            ],
            [
              1182.292242050171,
              11.985423872214055
            ],
            [
              1182.292242050171,
              11.9840805149649
            ],
            [
              1182.295503616333,
              11.982401309001862
            ],
            [
              1182.301082611084,
              11.98072209259387
            ],
            [
              1182.3112106323242,
              11.970478646400363
            ],
            [
              1182.312412261963,
              11.971318287751018
            ],
            [
              1182.316446304321,
              11.973669269652587
            ],
            [
              1182.3215103149414,
              11.974089085696615
            ],
            [
              1182.3261451721191,
              11.973921159357278
            ],
            [
              1182.334041595459,
              11.974928715827481
            ],
            [
              1182.3477745056152,
              11.967707811434812
            ],
            [
              1182.351551055908,
              11.964769016039673
            ],
            [
              1182.3557567596433,
              11.964265219335784
            ],
            [
              1182.3577308654785,
              11.965356777674412
            ],
            [
              1182.359790802002,
              11.9637614216932
            ],
            [
              1182.3625373840332,
              11.962333989941826
            ],
            [
              1182.365026473999,
              11.9637614216932
            ],
            [
              1182.3694896697998,
              11.963005723469317
            ],
            [
              1182.3755836486816,
              11.963425556076654
            ],
            [
              1182.3779869079588,
              11.966028503692307
            ],
            [
              1182.3786735534668,
              11.969555037901515
            ],
            [
              1182.3775577545166,
              11.977699476742607
            ],
            [
              1182.376184463501,
              11.982737151030117
            ],
            [
              1182.374038696289,
              11.983492794066043
            ],
            [
              1182.3731803894043,
              11.986767222776859
            ],
            [
              1182.371549606323,
              11.988278484166859
            ],
            [
              1182.3698329925537,
              11.990797234340114
            ],
            [
              1182.3696613311768,
              11.994239488211045
            ],
            [
              1182.3714637756348,
              11.996338401936226
            ],
            [
              1182.3749828338623,
              12.001207818852867
            ],
            [
              1182.3788452148438,
              12.004398078790713
            ],
            [
              1182.3833084106445,
              12.003054816051637
            ],
            [
              1182.3839950561523,
              11.99835334374157
            ],
            [
              1182.3857116699216,
              11.994323445073718
            ],
            [
              1182.3905181884766,
              11.9949950990341
            ],
            [
              1182.400131225586,
              11.984920114029151
            ],
            [
              1182.4011611938477,
              11.978874942482795
            ],
            [
              1182.4135208129883,
              11.967455915938498
            ],
            [
              1182.4210739135742,
              11.962753823592042
            ],
            [
              1182.4279403686521,
              11.95872339364665
            ],
            [
              1182.4296569824219,
              11.955364656152383
            ],
            [
              1182.4406433105469,
              11.94327285605027
            ]
          ]
        ]
      }
    },
    {
      "type": "Feature",
      "properties": {
        "name": "LaemNgop",
        "p": 500
      },
      "geometry": {
        "type": "Polygon",
        "coordinates": [
          [
            [
              1182.465877532959,
              12.16486956319579
            ],
            [
              1182.4501705169675,
              12.186347961286433
            ],
            [
              1182.422103881836,
              12.244398045927973
            ],
            [
              1182.4066543579102,
              12.26436030212715
            ],
            [
              1182.3881149291992,
              12.27257961539898
            ],
            [
              1182.3240852355957,
              12.24456580227236
            ],
            [
              1182.2918128967285,
              12.26050216871727
            ],
            [
              1182.267436981201,
              12.297403738358959
            ],
            [
              1182.2578239440918,
              12.291197927225324
            ],
            [
              1182.2593688964844,
              12.269895786197855
            ],
            [
              1182.264347076416,
              12.26855386134393
            ],
            [
              1182.2732734680176,
              12.25932794299426
            ],
            [
              1182.2876930236816,
              12.232151544966527
            ],
            [
              1182.2779083251953,
              12.208999075326542
            ],
            [
              1182.2811698913574,
              12.197757653273491
            ],
            [
              1182.3098373413086,
              12.183998846126931
            ],
            [
              1182.3251152038574,
              12.180475134396934
            ],
            [
              1182.334041595459,
              12.194569700524248
            ],
            [
              1182.3532676696777,
              12.193898547692125
            ],
            [
              1182.3659706115723,
              12.193898547692125
            ],
            [
              1182.3793601989746,
              12.183663256549302
            ],
            [
              1182.3857116699216,
              12.180642931254425
            ],
            [
              1182.388801574707,
              12.17560897939434
            ],
            [
              1182.3963546752927,
              12.169232503383142
            ],
            [
              1182.4344635009766,
              12.168980797242563
            ],
            [
              1182.4595260620115,
              12.163527105651713
            ],
            [
              1182.465877532959,
              12.16486956319579
            ]
          ]
        ]
      }
    }
  ]
}
